LICENSE
MANIFEST.in
README.rst
VERSION.txt
requirements.txt
setup.py
felis_python2/__init__.py
felis_python2/util.py
felis_python2.egg-info/PKG-INFO
felis_python2.egg-info/SOURCES.txt
felis_python2.egg-info/dependency_links.txt
felis_python2.egg-info/not-zip-safe
felis_python2.egg-info/requires.txt
felis_python2.egg-info/top_level.txt
felis_python2/lectures/01_Rewiew.ipynb
felis_python2/lectures/02_Numpy.ipynb
felis_python2/lectures/03_Scipy.ipynb
felis_python2/lectures/04_Scipy.ipynb
felis_python2/lectures/05_Scipy.ipynb
felis_python2/lectures/06_Scikit-image.ipynb
felis_python2/lectures/07_OpenCV.ipynb
felis_python2/lectures/08_pandas.ipynb
felis_python2/lectures/09_MachineLearning.ipynb
felis_python2/lectures/data/train.csv
felis_python2/lectures/data/train_corrected.csv
felis_python2/lectures/images/G.jpg
felis_python2/lectures/images/RGB.jpg
felis_python2/lectures/images/apple.jpg
felis_python2/lectures/images/beach.jpg
felis_python2/lectures/images/egg.jpg
felis_python2/lectures/images/filter.jpg
felis_python2/lectures/images/gauss.gif
felis_python2/lectures/images/hsv.jpg
felis_python2/lectures/images/image.jpg
felis_python2/lectures/images/image01.jpg
felis_python2/lectures/images/image02.jpg
felis_python2/lectures/images/image03.jpg
felis_python2/lectures/images/image04.jpg
felis_python2/lectures/images/opencv.png
felis_python2/lectures/images/scikit.png
felis_python2/lectures/images/sobel.gif
felis_python2/lectures/images/stanley.jpg
felis_python2/lectures/images/stool.jpg
felis_python2/lectures/images/that.gif
felis_python2/lectures/images/tree.jpg
felis_python2/lectures/images/var_types.JPG
felis_python2/lectures/images/zebra.gif