Metadata-Version: 1.0
Name: felis-python2
Version: 0.1.1
Summary: Lecture notes for Python 2 at University of Freiburg.
Home-page: UNKNOWN
Author: Mirko Mälicke
Author-email: mirko.maelicke@felis.uni-freiburg.de
License: MIT
Platform: UNKNOWN
